smart_text_randomizer/__init__.py
smart_text_randomizer/text_randomizers.py
smart_text_randomizer-0.0.4.dist-info/licenses/LICENSE
smart_text_randomizer-0.0.4.dist-info/METADATA
smart_text_randomizer-0.0.4.dist-info/WHEEL
smart_text_randomizer-0.0.4.dist-info/top_level.txt
smart_text_randomizer-0.0.4.dist-info/RECORD
