Metadata-Version: 2.4
Name: smart-text-randomizer
Version: 0.0.4
Summary: Smart Text Randomizer.
Home-page: https://github.com/smartlegionlab/smart-text-randomizer/
Author: A.A. Suvorov
Author-email: smartlegiondev@gmail.com
License: BSD 3-Clause License
Project-URL: Documentation, https://github.com/smartlegionlab/smart-text-randomizer/blob/master/README.md
Project-URL: Release notes, https://github.com/smartlegionlab/smart-text-randomizer/releases
Keywords: text randomizer,smart-text-randomizer,smartlegionlab,A.A. Suvorov
Classifier: Development Status :: 5 - Production/Stable
Classifier: License :: OSI Approved :: BSD License
Classifier: Natural Language :: English
Classifier: Operating System :: OS Independent
Classifier: Operating System :: POSIX :: Linux
Classifier: Programming Language :: Python :: 3 :: Only
Classifier: Topic :: Software Development :: Libraries :: Python Modules
Requires-Python: >=3.6
License-File: LICENSE
Dynamic: license-file
